MANIFEST.in
setup.py
farm_blast/__init__.py
farm_blast/blast.py
farm_blast/pipeline.py
farm_blast/utils.py
farm_blast.egg-info/PKG-INFO
farm_blast.egg-info/SOURCES.txt
farm_blast.egg-info/dependency_links.txt
farm_blast.egg-info/requires.txt
farm_blast.egg-info/top_level.txt
farm_blast/tests/blast_test.py
farm_blast/tests/pipeline_test.py
farm_blast/tests/utils_test.py
farm_blast/tests/__pycache__/blast_test.cpython-33.pyc
farm_blast/tests/__pycache__/pipeline_test.cpython-33.pyc
farm_blast/tests/__pycache__/utils_test.cpython-33.pyc
farm_blast/tests/data/pipeline_test.02.array.sh
farm_blast/tests/data/pipeline_test.03.combine.sh
farm_blast/tests/data/pipeline_test.blast.out
farm_blast/tests/data/pipeline_test.qry.fa
farm_blast/tests/data/pipeline_test.ref.fa
farm_blast/tests/data/pipeline_test.ref.indexed.fa
farm_blast/tests/data/pipeline_test.ref.indexed.fa.nhr
farm_blast/tests/data/pipeline_test.ref.indexed.fa.nin
farm_blast/tests/data/pipeline_test.ref.indexed.fa.nsq
farm_blast/tests/data/utils_test_coords_offset.tsv
farm_blast/tests/data/utils_test_fix_blast_coords.blast
farm_blast/tests/data/utils_test_fix_blast_coords.blast.fixed
scripts/farm_blast