Metadata-Version: 1.0
Name: farm-blast
Version: 0.1.2
Summary: Package to run blast in parallel on a compute farm
Home-page: https://github.com/sanger-pathogens/Farm_blast
Author: Martin Hunt
Author-email: mh12@sanger.ac.uk
License: GPLv3
Platform: UNKNOWN
